{"cameraMode":{"drawMode":0,"name":"Shaded","section":"Shading Mode"},"sceneLighting":true,"audioPlay":false,"sceneViewState":{"m_AlwaysRefresh":false,"showFog":true,"showSkybox":true,"showFlares":true,"showImageEffects":true,"showParticleSystems":true,"showVisualEffectGraphs":true,"m_FxEnabled":true},"in2DMode":false,"pivot":{"x":8.175383567810059,"y":3.3537933826446535,"z":-1.8351062536239625},"rotation":{"x":-0.00031210482120513916,"y":-0.9849514961242676,"z":0.001782717532478273,"w":-0.17283613979816438},"size":13.004105567932129,"orthographic":false}